pytextable/__init__.py
pytextable/_pytextable.py
pytextable-0.2.1.dist-info/LICENSE
pytextable-0.2.1.dist-info/METADATA
pytextable-0.2.1.dist-info/WHEEL
pytextable-0.2.1.dist-info/top_level.txt
pytextable-0.2.1.dist-info/zip-safe
pytextable-0.2.1.dist-info/RECORD
