Metadata-Version: 2.1
Name: pytextable
Version: 0.2.1
Summary: Utilities to convert python data to latex tables.
Home-page: https://github.com/karlch/pytextable
Author: Christian Karl
Author-email: karlch@protonmail.com
License: GPL3
Keywords: latex,tables,data
Platform: UNKNOWN
Classifier: Development Status :: 4 - Beta
Classifier: Environment :: Console
Classifier: Intended Audience :: Science/Research
Classifier: License :: OSI Approved :: GNU General Public License v3 or later (GPLv3+)
Classifier: Natural Language :: English
Classifier: Operating System :: POSIX :: Linux
Classifier: Programming Language :: Python :: 3 :: Only
Classifier: Programming Language :: Python :: 3.6
Classifier: Programming Language :: Python :: 3.7
Classifier: Programming Language :: Python :: 3.8
Classifier: Programming Language :: Python :: 3.9
Classifier: Topic :: Text Processing
Classifier: Topic :: Text Processing :: Markup :: LaTeX
Requires-Python: >=3.6
